vendorpy/__init__.py
vendorpy/cli.py
vendorpy/utils.py
vendorpy-0.1.0.dist-info/METADATA
vendorpy-0.1.0.dist-info/WHEEL
vendorpy-0.1.0.dist-info/entry_points.txt
vendorpy-0.1.0.dist-info/licenses/LICENSE
vendorpy-0.1.0.dist-info/RECORD
