Metadata-Version: 2.4
Name: vendorpy
Version: 0.1.0
Summary: Cloudflare Python workers vendoring CLI tool.
Project-URL: Homepage, https://bitnom.github.io/vendorpy/
Project-URL: Repository, https://github.com/bitnom/vendorpy
Project-URL: Documentation, https://bitnom.github.io/vendorpy/
Author-email: bitnom <14287229+bitnom@users.noreply.github.com>
License-File: LICENSE
Keywords: python
Classifier: Intended Audience :: Developers
Classifier: Programming Language :: Python
Classifier: Programming Language :: Python :: 3
Classifier: Programming Language :: Python :: 3.12
Classifier: Topic :: Software Development :: Libraries :: Python Modules
Requires-Python: <3.13,>=3.12
Requires-Dist: rich>=13.0.0
Requires-Dist: tomli-w>=1.0.0
Requires-Dist: tomli>=2.0.0
Requires-Dist: typer>=0.9.0
